intervaltree/__init__.py
intervaltree/interval.py
intervaltree/intervaltree.py
intervaltree/node.py
intervaltree-3.0.0.dist-info/LICENSE.txt
intervaltree-3.0.0.dist-info/METADATA
intervaltree-3.0.0.dist-info/WHEEL
intervaltree-3.0.0.dist-info/top_level.txt
intervaltree-3.0.0.dist-info/zip-safe
intervaltree-3.0.0.dist-info/RECORD
